Metadata-Version: 2.4
Name: logics
Version: 1.10.4
Summary: Logics is a Python framework for mathematical logic
Home-page: https://github.com/ariroffe/logics
Author: Ariel Jonathan Roffé
Author-email: arielroffe@filo.uba.ar
License: MIT
Classifier: Operating System :: OS Independent
Classifier: Programming Language :: Python
Classifier: Programming Language :: Python :: 3.6
Classifier: Programming Language :: Python :: 3.7
Classifier: Programming Language :: Python :: 3.8
Classifier: Programming Language :: Python :: 3.9
Classifier: Programming Language :: Python :: 3.10
Classifier: Topic :: Scientific/Engineering :: Mathematics
Requires-Python: >=3.6
License-File: LICENSE.txt
Requires-Dist: anytree>=2.8.0
Dynamic: license-file
